intronator/__init__.py
intronator/analysis.py
intronator/pangolin_utils.py
intronator/simple_api.py
intronator/spliceai_utils.py
intronator/splicing_utils.py
intronator/test_data.py
intronator/transcript_simulation.py
intronator-0.2.1.dist-info/licenses/LICENSE
intronator-0.2.1.dist-info/METADATA
intronator-0.2.1.dist-info/WHEEL
intronator-0.2.1.dist-info/top_level.txt
intronator-0.2.1.dist-info/RECORD
