Metadata-Version: 2.4
Name: intronator
Version: 0.2.1
Summary: A Python package for comprehensive splice site analysis and simulation
Home-page: https://github.com/intronator/intronator
Author: Intronator Team
Author-email: Intronator Team <contact@intronator.org>
Maintainer-email: Intronator Team <contact@intronator.org>
License-Expression: MIT
Project-URL: Homepage, https://github.com/intronator/intronator
Project-URL: Documentation, https://intronator.readthedocs.io
Project-URL: Repository, https://github.com/intronator/intronator
Project-URL: Bug Tracker, https://github.com/intronator/intronator/issues
Keywords: bioinformatics,splicing,genomics,splice-sites,RNA,mutations
Classifier: Development Status :: 3 - Alpha
Classifier: Intended Audience :: Science/Research
Classifier: Operating System :: OS Independent
Classifier: Programming Language :: Python :: 3
Classifier: Programming Language :: Python :: 3.10
Classifier: Programming Language :: Python :: 3.11
Classifier: Programming Language :: Python :: 3.12
Classifier: Topic :: Scientific/Engineering :: Bio-Informatics
Classifier: Topic :: Scientific/Engineering :: Artificial Intelligence
Requires-Python: >=3.10
License-File: LICENSE
Requires-Dist: seqmat
Requires-Dist: numpy>=1.21.0
Requires-Dist: pandas>=1.3.0
Provides-Extra: dev
Requires-Dist: pytest>=7.0; extra == "dev"
Requires-Dist: pytest-cov; extra == "dev"
Requires-Dist: black; extra == "dev"
Requires-Dist: isort; extra == "dev"
Requires-Dist: flake8; extra == "dev"
Provides-Extra: ml
Requires-Dist: torch>=1.10.0; extra == "ml"
Requires-Dist: tensorflow>=2.8.0; extra == "ml"
Requires-Dist: keras>=2.8.0; extra == "ml"
Requires-Dist: absl-py; extra == "ml"
Provides-Extra: external
Requires-Dist: spliceai; extra == "external"
Dynamic: author
Dynamic: home-page
Dynamic: license-file
Dynamic: requires-python
